PyDIVOC/__init__.py
PyDIVOC/divoc_qr.py
PyDIVOC-0.1.0.dist-info/LICENSE.md
PyDIVOC-0.1.0.dist-info/METADATA
PyDIVOC-0.1.0.dist-info/WHEEL
PyDIVOC-0.1.0.dist-info/top_level.txt
PyDIVOC-0.1.0.dist-info/RECORD
