Metadata-Version: 2.1
Name: PyDIVOC
Version: 0.1.0
Summary: Python library for decoding and verifying the COWIN Covid19 Credentials for India from DIVOC
Home-page: https://github.com/decentralised-dataexchange/pydivoc
Author: George J Padayatti
Author-email: george.padayatti@igrant.io
License: Apache Software License
Keywords: covid19,divoc,india,w3c credential
Platform: UNKNOWN
Classifier: Development Status :: 5 - Production/Stable
Classifier: Programming Language :: Python :: 3
Classifier: License :: OSI Approved :: Apache Software License
Classifier: Operating System :: OS Independent
Classifier: Topic :: Software Development :: Libraries :: Python Modules
Classifier: Intended Audience :: Developers
Classifier: Intended Audience :: Information Technology
Requires-Python: >=3.6.3
License-File: LICENSE.md
Requires-Dist: autopep8 (==1.5.7)
Requires-Dist: joblib (==1.0.1)
Requires-Dist: numpy (==1.21.0)
Requires-Dist: opencv-python (==4.5.2.54)
Requires-Dist: pycodestyle (==2.7.0)
Requires-Dist: toml (==0.10.2)
Requires-Dist: zbar-py (==1.0.4)
